{
    "title": "艺术家",
    "info": "   　　《艺术家》完全采用了传统的好莱坞叙事手法，讲述了默片时期著名男演员乔治和当时尚为群众演员佩比在偶尔的机会一见钟情，在他的推荐提携下佩比慢慢成名；与此同时，由于乔治拒绝接受有声电影即将取代无声片的事实，被电影公司解雇。他企图重新凭借一己之力，孤注一掷独自投资拍摄默片以求证明自己的艺术价值，结果不巧适逢经济大萧条时期，他的惨败让他一蹶不振，在企图自杀后又遭已成为巨星的佩比的帮助，最终两人终于团聚在一起。电影的结局是个载歌载舞的happy end。",
    "comment": [
        "2011年的复古版本，几乎倒退了100年志超看过 ",
        "一个精致、优雅的故事小眼儿天目看过 ",
        "一键2倍速，浓浓默片感！oleana看过 ",
        "中间第一次穿插声音时, 就很惊喜 和lala land一样, 满足了对那个年代好莱坞的好奇之外, 故事简单有趣, 也有深度 那狗狗真的太聪明啦沉思看过 ",
        "本以为是部很沉闷的文艺片，没想到拍的这么好看半城炊烟看过 ",
        "少有能让人耐心看完一部黑白默片，男主很有魅力四月柳丁看过 ",
        "一部可以感动自己的默片，简单更有穿透力。HopeTT看过 ",
        "默片时代和现代世界交织，有声电影和无声电影的碰撞，自我变化的剧烈。代号Spielberg看过 "
    ],
    "pic": [
        "http://img31.mtime.cn/mt/2012/12/13/095357.68340434_270X405X4.jpg"
    ],
    "actors": {
        "让·杜雅尔丹": [
            "        1995年杜雅尔丹第一次在白方剧院（Théâtre Carré Blanc）独立演出，同年他遇到了Eric Collado, Bruno Salomone, Emmanuel Joucla和Eric Massot，他们共同成立了一个叫“Nous C Nous”的喜剧表演团体。1996年“Nous C Nous”参加法国达人秀“巨星之源（Gaines de Star）”节目取得成功，那也是杜雅尔丹的名字首次为大众所知。        此后，在出演电影之前，从1999年到2003年，杜雅尔丹都在一个法国电视喜剧《一个小伙，一个姑娘（Un gars, une fille）》中出演一个名为Loulou的角色。",
            "http://img31.mtime.cn/ph/2014/03/14/152456.36051527_290X440X4.jpg"
        ],
        "贝热尼丝·贝乔": [
            " 　　贝热尼丝·贝乔，出生于阿根廷的法国女演员。她生于布宜诺斯艾利斯，她父亲是电影制片人米格尔·比约。3岁时贝热尼丝·贝乔搬到了法国居住并在以后从事表演行业。最知名的电影作品是2001年的《狂野武士》和2011年的《艺术家》。",
            "http://img31.mtime.cn/ph/2015/07/07/102054.59060533_290X440X4.jpg"
        ],
        "小狗乌吉": [
            " 　　虽然在默片《艺术家》中，你无法听到Uggie的叫声，但它的一举一动，甚至一个眼神，都足以证明其科班出身的功底。作为一名“表演专业户”，Uggie早在2005年的迪士尼电视电影《天才宝弟的狗日子》中就一展技艺，2011年它更是迎来事业井喷期，一连出演了《艺术家》和《大象的眼泪》两部知名电影，无论是“法国主人”让·杜雅尔丹，还是“马戏团好友”罗伯特·帕汀森，都对它赞不绝口。不幸的是，小狗长年受前列腺肿胀折磨，2015年8月7日与世长辞。 　　Uggie的专职训练师冯·穆勒曾评价“爱徒”：“以前，它经常是一个兴奋过头的小家伙。不过现在的它，绝对是这个行业内最训练有素的小狗之一。",
            "http://img21.mtime.cn/ph/2012/02/06/092700.90581947_290X440X4.jpg"
        ],
        "约翰·古德曼": [
            " 　　约翰·古德曼1952年6月20日生于美国密苏里州。拥有1.91米身高，超过150公斤体重的庞大身躯，大学时代与女星凯瑟琳·特纳是同班同学。1975年迁居纽约，分别在外百老汇和百老汇登台表演。也拍过一些电视广告片，1983年正式涉足影坛，开始在多部影片中担任配角，类型从硬汉，杀手到精神病患者不一而同，直至1991年的《肥龙皇帝》才首度出任主角。同年凭《巴顿芬克》一片扬威戛纳影展。　　在电视剧方面，约翰·古德曼以情景喜剧《Roseanne》最为出彩，曾先后5次入围金球奖，8次入围艾美奖，1993年终于捧回一座金球奖。",
            "http://img31.mtime.cn/ph/2014/03/21/093452.72436604_290X440X4.jpg"
        ],
        "詹姆斯·克伦威尔": [
            " 　　詹姆斯·克伦威尔1940年1月27日生于美国的加利福尼亚州。他曾先后在Carnegie-Mellon学院和Carnegie技术学校学习表演艺术。毕业后，和他的父母一样，在剧院进行莎士比亚戏剧的表演，积累了丰富的舞台表演经验。1974年，他开始出演电视剧。1976年，詹姆斯·克伦威尔拍摄了自己的首部电影《徒步者南茜》。他是一个地道的素食主义者。　　1996年，他出演了著名的科幻系列电影《星际旅行：第一类接触》。1995年，詹姆斯·克伦威尔凭借电影《小猪宝贝》中农夫亚瑟一角获得奥斯卡最佳男演员奖的提名。在奥斯卡最佳男演员提名者中，身高1.98米的詹姆斯·克伦威尔鹤立鸡群，是最高的一位。",
            "http://img31.mtime.cn/ph/2013/01/17/100205.74488248_290X440X4.jpg"
        ],
        "佩内洛普·安·米勒": [
            " 　　美国女演员。她的职业生涯从百老汇开始，并在几部好莱坞大制作电影中出演过角色，尤其是在1990年代早期，现在仍然出现在电影和电视中。由于出演戏剧，曾经获得过托尼奖的提名。　　她曾与好莱坞最杰出的男演员和导演合作过。包括在布莱恩德帕尔玛的《情枭的黎明》中与阿尔帕西诺和西恩潘演对手戏，在安德鲁·伯格曼的《新生》中和马龙·白兰度与马修·布罗德里克有过合作，在《唤醒》中与罗伯特·德尼罗和罗宾·威廉斯的合作等等。",
            "http://img31.mtime.cn/ph/2014/02/22/203714.95942221_290X440X4.jpg"
        ],
        "米西·派勒": [
            " 出生在得克萨斯州，，但在成长在田纳西州。1995年毕业于北卡罗来纳州艺术学院。一开始她出现在各种电视节目中。于1997年的电影《尽善尽美》中一个小配角开始登上银幕。之后在《银河追缉令》中的角色让她取得了一定的突破，之后出演了大量的电影，但以演出各种小配角为主。",
            "http://img31.mtime.cn/ph/2015/06/25/155531.47197605_290X440X4.jpg"
        ],
        "贝丝·格兰特": [
            " 　　贝丝·格兰特在美国南方长大，童年时期经常搬家，喜欢把亚拉巴马州，佐治亚州和北卡罗来纳州的好多地方都称为家。她在北卡罗莱纳州参议院见习过，参加了北卡罗莱纳州州长的资优学生的学校，并在十九岁获得总督任命。　　好莱坞最熟悉的面孔之一，她曾主演过七十多部电影，创造了一系列丰富多彩的角色。作为演员，她涉猎范围很广，从戏剧，电影到电视都有涉及。此外，格兰特还是身兼制作人和导演的角色，她制作纪录片，喜剧和电视，她还运行着一个剧团，为学校筹集资金，并为卡特的第一次总统竞选名人协调员。格兰特是一个行动派的人物。",
            "http://img31.mtime.cn/ph/2014/03/14/154515.92647770_290X440X4.jpg"
        ],
        "艾德·劳特": [
            " 　　艾德·劳特，美国演员，出生在纽约，他的大银幕处女作是1972年的《肮脏的小比利》，入行以来出演过近百部的电影及电视剧作品。他最近一部最受关注的作品是获得第84届奥斯卡提名的电影《艺术家》。",
            "http://img31.mtime.cn/ph/2015/09/16/150721.69432414_290X440X4.jpg"
        ],
        "乔尔·默里": [
            " 　　乔尔·默里，美国演员。出生在美国伊利诺斯州，成长在一个爱尔兰天主教的家庭，家中有9个兄弟姐妹。他的第一个电影角色是1986年的喜剧电影《炎夏春色艳无边》的乔治乌贼，1992年出演了喜剧片《摆晃小丑》，2011年他参演了《艺术家》、《无耻之徒》两部备受欢迎的电影。",
            "http://img31.mtime.cn/ph/2014/09/26/171415.73042510_290X440X4.jpg"
        ]
    }
}