{
    "title": "万圣节",
    "info": "   1963年万圣节。小镇哈登菲尔德的一个6岁男孩麦克尔·麦尔斯用一把菜刀杀死了姐姐，当他的父母发现他时，他正手攥着那把血淋淋的杀人凶器直瞪瞪望着天空，于是被送进精神病院。尽管医生努力诊治，但他还只是坐着，眼瞪着天空。15年后，他返回小镇。接着发生的事情令人毛骨悚然。",
    "comment": [
        "看得出来的低成本，表演生涩，化妆简陋，节奏慢得一度有些煎熬。但是导演风格很喜欢，镜头给得特别好，整体比猛鬼街好太多，也更恐怖。对了，配乐满分。猜测导演本身并没有想拍续集，最后的镜头还是想说the shape可能在任何人家，这是最招人烦的地方了-_-!!!太子巴德看过 ",
        "当年的经典现在来看显得比较粗糙。砍杀部分比较少，节奏很慢，人物智商欠费。但作为这一系列的鼻祖，依然有其独特的魅力。八爪看过 ",
        "忘记了·DHW·看过 ",
        "在最后20分钟前，都觉得还行，虽然恐怖的镜头不多，但是整体的氛围和节奏感觉控制的还行，有一点紧张感，故事也还算有趣，但是到了最后高潮部分就真的一下子蠢哭了，我可以理解凶手这种狩猎心态，他不追不跑，慢慢靠近，这ok的，但是一直这样，女主角还蠢的不行就真的有点让人看不下去了，特别是到了这个年代，我们在电影里看到越来越多坚强聪明厉害的女性角色，再看看这个女主角，就真的觉得没有啥存在的价值，但是总得来说，是开创了一个类型片影迷姜2看过 ",
        "这看来还是个系列~Victor1314看过 ",
        "作为这个伟大系列的鼻祖，还可以。配乐太经典。不经意的转弯看过 ",
        "非常经典。很庆幸自己在40年后的万圣节看了这场经典恐怖片。全场一阵阵的爆笑驱散了我的惊恐……十Diez看过 ",
        "音乐太赞了！如果关掉声音这片儿的体验要减一大半儿。“尖叫女王”的嘶喊里带着哭腔，特别真实。彭小母看过 "
    ],
    "pic": [
        "http://img5.mtime.cn/mg/2017/04/01/231945.43769661_270X405X4.jpg"
    ],
    "actors": {
        "唐纳德·普利森斯": [
            "",
            "http://img21.mtime.cn/ph/2010/06/21/154750.34129070_290X440X4.jpg"
        ],
        "杰米·李·柯蒂斯": [
            " 杰米·李·柯蒂斯是好莱坞大明星托尼·柯蒂斯与珍妮特·李的女儿，1958年生于加州洛杉矶。1978年以恐怖片《月光光心慌慌》进入影坛。而后她主演了相当多的惊悚片，因此她被称作“尖叫女皇”，视作惊悚片的代言人。但事实上她也并仅局限于恐怖惊悚片，她曾主演过不少其他类型的著名影片，如1983年的喜剧片《你整我，我整你》，1988年的黑色犯罪片《一条名叫旺达的鱼》，对于中国观众最为熟悉的应该是1992年的大片《真实的谎言》，而正是因为她在此片中的出色表演使她赢得了一座金球奖。在1998年她又主演了《月光光心慌慌》的续集《大屠杀》，一个出色的回归。",
            "http://img21.mtime.cn/ph/2011/10/26/142818.27698268_290X440X4.jpg"
        ],
        "·索尔丝": [
            "",
            "http://img31.mtime.cn/ph/2014/02/22/201344.17146059_290X440X4.jpg"
        ],
        "凯尔·理查兹": [
            "",
            "http://img31.mtime.cn/ph/785/1066785/1066785_290X440X4.jpg"
        ]
    }
}