{
    "title": "一步之遥",
    "info": "   北洋年间，东方魔都，花域大选如火如荼，各国佳丽争相斗艳，万众瞩目，全城狂欢，两届总统完颜英（舒淇饰）惊险连任，大选操办人马走日（姜文饰）因此名满天下。然而一场谋杀颠覆了一切，完颜英命丧黄泉，马走日亡命天涯，并和操办大选的另一搭档、发小项飞田（葛优饰）由莫逆之交变为生死宿敌，而将府名媛武六（周韵饰）的出现，改变了所有人的命运，魔都双雄展开生死对决，惊天冒险一触即发，生死爱恋一步之遥……",
    "comment": [
        "如果删减那场德云社混搭百老汇的那场闹剧，还有舒淇姜文那段王朔式的抖机灵对话，我觉得电影可能更完整，也更容易让大众接受一些。但是这不并影响整个故事的叙述，那段荒诞的恋爱戏反而是我熟悉的姜文。带着江湖混混气和北京人特有戏谑的那种浪漫。故事挺好懂的，也不需要过多的解读和引申，段子式的台词中表现出每个人的性格，故事也有趣，挺对我胃口的。颖郎轩看过 ",
        "不知所云李鑫看过 ",
        "故事还是那个故事，有点飘地夹带了很多私货，姜文大概是不想用类型片的方式叙述。隐喻什么的还是看表，往里子里解读就失去了味道。秋雁将何归看过 ",
        "我是来看周韵，舒淇，葛优和姜文的，所以故事是其次了。加勒比樱桃看过 ",
        "一部失去平衡失去节奏失去最基本的可读性最终完全失控的作品。水手辛伯达看过 ",
        "不知所云。。。红柿出墙看过 ",
        "不成功，我觉得首先要在故事讲好的基础上讨论增加隐喻，不然就很傻了，结果就成了姜文的个人狂欢，本末倒置，流于形式，我到现在都想不清楚歌舞这么长时间干嘛。汲哲看过 ",
        "爱奇异-隐喻什么的看不出来，但故事还是很有趣的蔡正一看过 "
    ],
    "pic": [
        "http://img31.mtime.cn/mg/2014/11/12/164234.89589229_270X405X4.jpg"
    ],
    "actors": {
        "姜文": [
            " 　　原名姜小军，河北唐山人。1980年进入中央戏剧学院表演系学习。于1984年毕业。同年进入中国青年艺术剧院，主演了《家庭大事》《高加索灰阑记》等优秀话剧剧目。1985年拍摄第一部电影《末代皇后》，参加叙利亚第5届大马士革国际电影节， 获得巴西第4届里约国际电影电视节获评委会特别奖。　　1986年，主演谢晋导演的电影《芙蓉镇》，获中国第十届百花奖最佳男演员奖。1987年，主演中法合拍影片《花轿泪》。1987年，主演张艺谋导演的电影《红高粱》。1988年，主演电影《春桃》，获中国第十二届百花奖最佳男演员奖。1989年，主演电影《本命年》。1990年，主演电影《大太监李莲英》。",
            "http://img5.mtime.cn/ph/2018/02/07/110510.14763357_290X440X4.jpg"
        ],
        "葛优": [
            " 　　1957年出生于北京，后在昌平农村劳动，1979年入全国总文工团话剧团从事舞台剧表演。1985年拍摄了第一部影片《盛夏和她的未婚夫》。真正给葛优带来星运的是1988年由王朔小说改编的影片《顽主》，他的外型与表演都恰合了王朔笔下那种“冷面热心”幽默成性的小人物，他扮演的银幕形象显得轻松、到位，获当年金鸡奖最佳男演员奖提名。从此，葛优星运亨通。以他的喜剧最为出名，以正剧奠定他在影坛的地位。　　1989年，藤文骥的《黄河谣》，葛优演来有声有色。接着，葛优又在黄健中的《过年》中饰演好色委琐又假正经的大姐夫，赢得了“百花奖”最佳男配角奖。1993年陈凯歌的影片《霸王别姬》中又有葛优精彩的表演。",
            "http://img31.mtime.cn/ph/2014/03/14/153507.63821000_290X440X4.jpg"
        ],
        "周韵": [
            " 毕业于中央戏剧学院表演系，出道拍的第一个广告片就与梁朝伟合作，接下来的第一部电影是与姜文、中井贵一、赵薇等大牌明星合作的《天地英雄》，主演的第一部电视剧《走过幸福》又和孙红雷演的对手戏，二人都表现不俗。周韵用完全自然的表演风格饰演的“朱小北”，几乎成为2003年演艺圈所有人的欣喜发现。《走过幸福》同时让周韵真正走进了千家万户。周韵和姜文相识于《天地英雄》剧组，影片完成后两人还保持着联系，随着对对方理解的加深，姜文与前妻协议离婚后，于2005年底和她正式注册结婚。2006年两人合作了《太阳照常升起》，随后继续合作了《让子弹飞》、《一步之遥》、《邪不压正》等片。",
            "http://img31.mtime.cn/ph/2014/12/21/105043.14635297_290X440X4.jpg"
        ],
        "舒淇": [
            " 　　原名林立慧。童年时代家境贫寒，从高中起就不再读书，为了赚钱养家，她当上了业余模特。1996年从台湾到香港发展，被王晶发掘，主演三级片《红灯区》、《玉蒲团之玉女心经》等，一脱成名。后接演尔冬升的《色情男女》，包揽香港电影金像奖最佳女配角、最佳新人两项大奖，成为香港电影史上唯一一位拍三级片获此殊荣的女星。获奖后人气大增，接片时也更注重影片质量，几年间接演影片达数十部，文艺片商业片兼具。",
            "http://img31.mtime.cn/ph/2016/04/16/110217.81063005_290X440X4.jpg"
        ],
        "文章": [
            " 　　文章，陕西西安人，中国内地男演员。毕业于中央戏剧学院表演系，爱好音乐、足球、游泳、书法、阅读等。文章的父母都是公务员，优厚的家庭条件决定了他童年的一帆风顺。因而，他从小就受到良好教育。　　　　　　　　　　　　　　　　　　　　　　　　　　　　　　　　　　　　　　　1999年，还在上中专艺校的文章就出来拍戏了，但都是饰演一些小角色。2004年，还在中央戏剧学院表演系读书的文章，在《与青春有关的日子》中成功饰演了卓越。虽然只是一个配角，但是他让文章逐渐为观众所熟悉。之后，他又在《奋斗》、《暗流》、《蜗居》、《雪豹》、《海洋天堂》等影视剧作中有突出表现，曾在2003年韩国釜山艺术节上，获“最佳男演员奖”。",
            "http://img5.mtime.cn/ph/2017/06/26/100352.52021977_290X440X4.jpg"
        ],
        "刘利年": [
            "",
            "http://img31.mtime.cn/ph/2016/08/31/165156.13756465_290X440X4.jpg"
        ],
        "洪晃": [
            " 洪晃，著名文人章士钊的外孙女、外交家乔冠华的继女、作家章含之的女儿、导演陈凯歌的前妻。1961年生于北京。12岁时被外交部送往纽约学英文。1984年毕业于美国纽约州瓦瑟大学。曾经做过咨询、有色金属贸易、投资等业务。现为出版人。",
            "http://img31.mtime.cn/ph/2014/05/13/090016.30428848_290X440X4.jpg"
        ],
        "王志文": [
            " 　　中国内地男演员。出生在上海。祖籍浙江奉化。1984年考入北京电影学院表演系，毕业后分配在中央戏剧学院表演系任教至今。　　虽然出道较晚，但他对人物的把握深刻，因在电视连续剧《皇城根儿》中的一个青年扮相一举成名，之后接戏不断，先后主演了影片《芬妮的微笑》、《说出你的秘密》、《荆轲刺秦王》、《半生缘》、《风云之雄霸天下》、《秘密采访》、《红粉》、《敌后武工队》、《紧急救助》、《超寻》等。在电视连续剧《DA师》、《黑冰》、《过把瘾》、《东边日出西边雨》、《杀人街的故事》、《无悔追踪》《南行记》、《皇城根儿》、《刑警本色》、《让爱作主》中均有精彩亮相。",
            "http://img31.mtime.cn/ph/2016/09/08/150924.10264046_290X440X4.jpg"
        ],
        "那英": [
            "",
            "http://img31.mtime.cn/ph/2014/05/23/101702.72975779_290X440X4.jpg"
        ],
        "姜洪齐": [
            "",
            "http://img31.mtime.cn/ph/2016/08/26/133419.43934898_290X440X4.jpg"
        ]
    }
}