{
    "title": "时间旅行者的妻子",
    "info": "   　　亨利是一位年轻帅气、爱冒险的图书管理员。他有慢性“时间错位症”，会不知不觉地游离在时间之外。他以为他在28岁时第一次遇到他20岁的妻子克莱尔，而克莱尔却说“我从小就认识你了”；和克莱尔结婚多年后，亨利又突然发现自己回到了童年，遇见了他6岁的妻子……时间过滤着这一对恋人炙热的爱意。一个奇幻的假设造就了一个荡气回肠的爱情故事。他一次又一次把爱人远远地抛在了身后，她却用一生的时间等待爱人回到身边。... ",
    "comment": [
        "一旦接受了这个故事设定，影片本身就没什么看点了。自由彼岸看过 ",
        "时空穿梭爱情片，爱情是主题，穿梭是外衣。女主角瑞秋•麦克亚当斯很漂亮，但有的地方表演有点儿尬。有几个穿越桥段设计的挺不错。但结尾的穿越有点儿问题。感觉想模仿《返老还童》若即若离的爱情模式，但整体略显平淡。书生偷香看过 ",
        "或许一个人连带肉体一起，也是也一具灵魂，一样吧！人生几多颠覆看过 ",
        "好看。时空方面不是很清晰，按前部分推理，主角不应该穿梭到未来，因为他不知道之后发生的事情。很多地方都经不起推敲，不过不妨碍观看。女主，誓约里的女主，喜欢。总体说，推荐。黑鹰v电影篇看过 ",
        "记忆，命运，可以用这样的手法来表现，，10多年前初看时，被烧脑的穿越吸引，，如今再看，其实是简单的命题hzsimonlin看过 ",
        "很有意思的故事星璇风看过 ",
        "希望有一天他们还能相见啊华丽的低调5202047看过 ",
        "我若爱你，会错过余生；可不爱你，就错过一生。李比廉姆看过 "
    ],
    "pic": [
        "http://img31.mtime.cn/mt/2014/02/23/044440.10777083_270X405X4.jpg"
    ],
    "actors": {
        "艾瑞克·巴纳": [
            " 　　艾瑞克·巴纳1968出生于澳大利亚墨尔本，父亲是克罗地亚人，母亲则是德国人。小时候的他立志当个机械工，中学时还因此兴起休学的念头，想直接到汽车厂工作，最后这个叛逆的念头终因父亲的劝告而打消。几年之后因为喜欢看喜剧演员理察德·普里尔的演出，开始对演戏感兴趣，但一直到看了电影《MadMax》后才下定决心要当个演员。事后看来，演员理察德·普里尔和喜剧的确对艾瑞克的表演生涯有不小的影响：他在正式担任电影演员前，演了了十年的舞台喜剧单口相声；和多才多艺的理察德·普里尔一样，他也对编导工作跃跃欲试，并曾担任过几部戏剧的幕后工作。",
            "http://img31.mtime.cn/ph/2014/04/23/171547.32479537_290X440X4.jpg"
        ],
        "瑞秋·麦克亚当斯": [
            " 　　1976年10月7日在加拿大出生。2004年她出演了由美国著名的言情畅销书作家尼古拉·史帕克(Nicholas Sparks)创作的同名小说改编而成的电影《恋恋笔记本》，这是个关于爱情和回忆的故事。饰演艾丽的瑞秋·麦克亚当斯在两年以前，还住在加拿大时，就想着如何开始她的演艺生涯。　　不久之后，这个神话般的女孩吸引了好莱坞的注意，出现在《变身辣妹》里，那是在2002年她饰演的角色非常成功，也在一夜之间使她成为了全美国的青春偶像明星，随后在热门青春喜剧片《贱女孩》中饰演校花。她在《恋恋笔记本》中饰演女主角，虽然要比饰演男主角的瑞恩·高斯林大4岁，不过他们都同样出生在加拿大，性格气质上非常接近。",
            "http://img31.mtime.cn/ph/2014/03/14/200200.57045741_290X440X4.jpg"
        ],
        "阿莱克斯·费瑞斯": [
            "",
            "http://img31.mtime.cn/ph/2014/02/22/212103.39099948_290X440X4.jpg"
        ],
        "米歇尔·诺尔顿": [
            "",
            "http://img5.mtime.cn/ph/2016/09/05/140552.65010988_290X440X4.jpg"
        ],
        "艾利斯·霍华德": [
            "",
            "http://img31.mtime.cn/ph/1623/905623/905623_290X440X4.jpg"
        ]
    }
}