{
    "title": "秒速5厘米",
    "info": "   “我该用什么样的速度去生活，才能与你相逢？”远野贵树和筱原明里是同班同学，他们都从别的城市转入东京的这所小学，都喜欢看书，因此特别谈得来。贵树天真地以为能永远和明里在一起。然而，小学毕业后，明里跟随家人离开了东京。两人的生活从此不再有交集，只能用书信来传达彼此的思念。岁月不断流逝，少年渐渐长大。贵树决定无论如何都要去见明里一面。终于，在一个大雪天，他带着满心的期盼坐上了开往远方的列车……这部电影由三个短片构成，描绘出一段成长与爱的故事。第一话《樱花抄》述说两位主人公的重逢。第二话《宇航员》从暗恋贵树的女孩——花苗的视角来展现贵树与明里分别后的生活。第三话《秒速5厘米》则刻画了贵树和明里长大后内心的种种彷徨。",
    "comment": [
        "还是佩服日本这种纯爱故事，电影更像是小品文，故事非常非常简单。电影的讲述、语气，电影的画风、色彩，还有少年们的懵懂，都让这个故事一般都不一般天行者aiken看过 ",
        "校园爱情题材，辅以科幻元素，关乎成长。优美的画风，与校园情景贴切，而包括片尾共计4个章节的划分，则慢慢发出了终究抵不过时间和距离的感慨，感慨大于故事，故事性较弱，且60分钟的篇幅划为4个段落，本身也说明剧情联动性不足……倒影·倒映看过 ",
        "可能经历还不够多，没啥感觉。作画不错。Hibixis看过 ",
        "三段故事，一个人物不同阶段，个人不喜欢这样的情感表达artistfx看过 ",
        "长大后回忆那些青涩的青春都是那么唯美和遗憾并非如果看过 ",
        "画面好评，结尾的歌曲好评。樱花飘落的盛世美景，不知何时还能再见啊……Dwarf看过 ",
        "多年前看过的影片，现在看来却有更深的感触，或许是年岁增长的缘故吧。有人说，新海诚并不擅长讲故事，他只是营造出一种特别的氛围。但这种“特别的氛围”却击中了我的心，在电影结束许久后我仍未释怀。谁的青春没有一些浪漫的故事呢？但拥有童话结局的幸运儿只是少数，大部分人的青春只能用来怀念……最后，《秒五》的音乐和画面怎么夸奖都不过分。灰港的造船者看过 ",
        "若只是排解寂寞，谁都可以替代。（秒速五厘米）。遗憾的我们才会懂得。马明77看过 "
    ],
    "pic": [
        "http://img5.mtime.cn/mg/2019/08/02/173713.13751369_270X405X4.jpg"
    ],
    "actors": {
        "水桥研二": [
            "",
            "http://img31.mtime.cn/ph/2014/02/22/203554.72731955_290X440X4.jpg"
        ],
        "近藤好美": [
            "",
            "http://img31.mtime.cn/ph/2014/02/22/213907.57459855_290X440X4.jpg"
        ],
        "尾上绫华": [
            "",
            "http://img31.mtime.cn/ph/2014/02/22/213907.81645486_290X440X4.jpg"
        ],
        "花村怜美": [
            "",
            "http://img31.mtime.cn/ph/2014/03/14/154139.17975590_290X440X4.jpg"
        ],
        "水野理纱": [
            "",
            "http://img31.mtime.cn/ph/1319/1471319/1471319_290X440X4.jpg"
        ],
        "寺崎裕香": [
            "",
            "http://img31.mtime.cn/ph/313/1246313/1246313_290X440X4.jpg"
        ],
        "中村优子": [
            "",
            "http://img21.mtime.cn/ph/2011/12/15/123420.16894067_290X440X4.jpg"
        ],
        "岩崎征实": [
            "",
            "http://img31.mtime.cn/ph/958/1368958/1368958_290X440X4.jpg"
        ]
    }
}