{
    "title": "湄公河行动",
    "info": "   2011年10月5日，两艘中国商船在湄公河金三角水域遭遇袭击，13名中国船员全部遇难，泰国警方从船上搜出90万颗冰毒。消息传回国内，举国震惊。为了查明真相，云南缉毒总队长高刚（张涵予饰）接受了特殊任务，率领一支骁勇善战的战斗小组进入泰国境内，与潜伏在泰国的情报员方新武（彭于晏饰）碰头，二人联手深入金三角查案。经过调查，发现案件背后果然有着重重疑点，真正的凶手在嫁祸残害无辜中国船员后，不但逍遥法外，更意图利用毒品制造更大的阴谋……二人决定，不惜一切代价也要拿下真凶，打击毒品犯罪，为无辜国人讨回公道！",
    "comment": [
        "一个挺好的真是事件，被瞎改的乌七八糟面目全非，中国电影水平真的一般一般西北偏西YBC看过 ",
        "这样的主旋律系列电影几部看下来，毛病还是那几个，最大的就是感受不到电影艺术的质感，其实这样的真事改编并不需要过多的加工，反而偏离了真实OKB",
        "故事很好，因为背景很真实，不过看完之后最大的感触就是兔子将来需要怎么定位跟东南亚的关系呢？cavalry看过 ",
        "太艰难了，致敬。金三角没完没了，走一个来一个的，也没啥办法，唉芥色看过 ",
        "啸天……😭离家去重庆之前看的。重温已是斗转星移的三年后…八卦松储会看过 ",
        "杀不完的毒贩，可怜的啸天！可拉_278639172看过 ",
        "杀人偿命，欠债还钱！撒旦St看过 ",
        "国家行动很多时候要靠成龙那样孤单英雄来实现。片子还应该拿出笔墨交代谋划，另外节奏掌握很差。啼笑因缘看过 "
    ],
    "pic": [
        "http://img5.mtime.cn/mg/2016/09/14/094849.74245579_270X405X4.jpg"
    ],
    "actors": {
        "张涵予": [
            " 　　配音演员出身的张涵予曾为《指环王》、《特洛伊》等大片配过音，而近年也不断“触电”，在《贻笑大方》、《贫嘴张大民的幸福生活》、《梦开始的地方》等电视剧及《集结号》、《风声》等电影里，张涵予游走在各类角色中，给观众留下深刻印象。 　　虽然是干配音起家，可从严格意义上说，张涵予不算真正的配音演员，因为他的专业是在中戏学的表演，干上配音工作纯粹是因为喜欢。读高中时，他就到中央电视台译制片组给外国影片配音，算起来跟现在的少儿节目主持人董浩是一拨儿。　　最初让张涵予“上瘾”的是一部电视剧，名叫《梦开始的地方》，跟陶虹配戏，结果他的表演梦竟然真的开始了。而接二连三地与冯小刚合作，也让张涵予越来越火起来。",
            "http://img31.mtime.cn/ph/2016/01/08/102820.24124767_290X440X4.jpg"
        ],
        "彭于晏": [
            " 　　彭于晏，出生于台湾。13岁和家人移民到加拿大，进入加拿大英属哥伦比亚大学，主修经济学。原以为自己会走上从商之路，然而升大二暑假外婆过世，彭于晏回台奔丧，然后遇到了小时候拍广告认识的导演杨大庆，找他演出了偶像剧《爱情白皮书》中的男二号，从此进入演艺圈。　　彭于晏回忆说：“我抱持打工的心情去尝试，当时也没签任何合约就去拍戏。”因而进入演艺圈而休学专心拍片。",
            "http://img5.mtime.cn/ph/2016/11/14/111046.75660912_290X440X4.jpg"
        ],
        "陈宝国": [
            " 生于天津，1977年考入中央戏剧学院表演系。毕业后分配到中国儿童艺术剧院工作。十多年来，在数十部电影、话剧和电视剧中扮演重要角色。丰富的创作实践和成果，使他成为名副其实的影视剧三栖演员，有“冷面小生”之美誉。1980年以来，他相继在影片《大渡河》、《一路顺风》、《默默的小理河》、《天使与魔鬼》、《暂缓逮捕》中饰演了重要角色。1986年陈宝国在影片《神鞭》中饰演“混混儿”玻璃花一角，他将体验与体现外部形体动作和内心情感有机统一起来，通过玩扇子和鼻烟壶，挖耳朵、修指甲等细部动作丰富人物形象，为他的瞎眼和跛脚找出生活依据，演活了这个人物，受到观众好评。",
            "http://img5.mtime.cn/ph/2017/03/09/094547.33313036_290X440X4.jpg"
        ],
        "孙淳": [
            " 中国影视演员。1956年生于山东济南。1982年毕业于上海戏剧学院表演系。后任峨眉电影制片厂演员。1982年首次参加演出《见习律师》。他主演的影片《大阅兵》获1987年第11届蒙特利尔国际电影节评委奖和意大利都灵青年国际电影节大奖；《留守女士》获1992年第16届开罗国际电影节最佳影片金字塔奖。孙淳是一位实力相当不俗的演技派，出道很早，但却始终没有赢得应该具备的知名度。他是陈凯歌的《大阅兵》的一号男主角，他在张艺谋的《摇啊摇，摇到外婆桥》中也有上佳的表现。电视剧《走向共和》中，他为饰演窃国大盗袁世凯，增肥数十斤。",
            "http://img31.mtime.cn/ph/2014/08/15/095230.68809269_290X440X4.jpg"
        ],
        "冯文娟": [
            " 　　冯文娟，内地新生代女星。2012年毕业于中央戏剧学院表演系，以清新的外形被香港著名导演王晶、刘伟强相中，参与拍摄了贺岁档大片《大上海》，在片中与黄晓明上演对手戏，得到导演好评。",
            "http://img5.mtime.cn/ph/2019/02/21/181442.63194251_290X440X4.jpg"
        ],
        "刘显达": [
            "",
            "http://img5.mtime.cn/ph/2016/09/28/165255.36566735_290X440X4.jpg"
        ],
        "赵健": [
            "",
            "http://img31.mtime.cn/ph/2016/08/26/162816.56805446_290X440X4.jpg"
        ],
        "吴旭东": [
            "",
            "http://img31.mtime.cn/ph/2014/12/29/102849.96678665_290X440X4.jpg"
        ],
        "战立国": [
            "",
            "http://img5.mtime.cn/ph/2016/09/28/165611.53631896_290X440X4.jpg"
        ],
        "柏华力·莫高彼斯彻": [
            "",
            "http://img5.mtime.cn/ph/2016/10/07/124742.68983560_290X440X4.jpg"
        ]
    }
}