{
    "title": "空中监狱",
    "info": "   　　凯奇饰演的凯梅龙·坡是一个现代罗宾汉，他若见到好人被欺负、特别是妇女遭调戏，一定拔刀相助。他作为一个即将假释的囚犯，坐上了全美最十恶不赦罪犯的专机，他的头顶几乎带上了圣人的光环。他那身穿白背心、浑身肌肉、逃离火海的造型颇有男性气概。他的对手不是常见的乌合之众，借用其中一人的话，他们是“国宝”级的高手，他们杀人不是出于不得已，而是视之为一门艺术。",
    "comment": [
        "很棒~非常喜欢的一部电影KOBEZHENG看过 ",
        "凯奇在这里太帅了，英雄式的人物，他妻子太美了宛若angel看过 ",
        "儿时的经典孔雀看过 ",
        "凯奇在《变脸》和《空中监犾》中帅得掉渣天天向上1567454看过 ",
        "凯奇最爷们儿的一部电影，马尔科维奇扮演的大反派也相当出彩，可惜他俩都没获奖……美式迪达拉看过 ",
        "我欣赏不来维她柠檬茶看过 ",
        "凯奇是从什么时候开始成为烂片之王的呢？守塔人看过 ",
        "啊~进时光看到已经评分原来我看过了吗！那么五一重温了凯奇，原来你曾是肌肉凯奇~这个撞击在97年肯定相当了不起！juile看过 "
    ],
    "pic": [
        "http://img31.mtime.cn/mt/2014/02/22/225042.41666287_270X405X4.jpg"
    ],
    "actors": {
        "尼古拉斯·凯奇": [
            " 　　尼古拉斯·凯奇出生于1964年1月7日，他本姓科波拉，是以《教父》和《现代启示录》等片闻名于世的大导演科波拉的侄子。作为科波拉家族的一员，他从小就在充满音乐与书籍的环境中长大，并养成了喜欢观察的习惯。同时成为一名电影演员也是他长久以来的梦想。 　　　　　　　　1982年，尼古拉斯在影片《开放的美国学府》中获得了一个角色，这是他从影的首部作品。次年他又参加与了影片《山谷女郎》和《斗鱼》的演出。《斗鱼》是由凯奇的叔叔科波拉执导的影片。为了与叔叔相区别，凯奇决定他需要一个属于自己个人的身份，最后定下了凯奇这个名字。　　　1984年，在名片《鸟人》中，凯奇出任了主角。",
            "http://img31.mtime.cn/ph/2014/03/14/153700.85813494_290X440X4.jpg"
        ],
        "约翰·库萨克": [
            " 　　约翰·库萨克生于芝加哥的一个电影世家：父亲是电影制片人，兄弟姐妹都是演员。约翰·库萨克在12岁成为芝加哥的 Piven 剧场工作室一名成员，为电影配音。17岁初登银幕，此后一直饰演乳臭未干的青少年角色。1997年是约翰·库萨克的转型之年。他在电影《午夜善恶园》(Midnight in the Garden of Good and Evil)出色饰演一名联邦探员而获得独立精神奖的最佳男演员提名。近年来约翰仍然坚持着对独立电影的钟爱，出演了不少优秀作品，成为影迷心目中独具个性的性格演员。",
            "http://img31.mtime.cn/ph/2016/08/29/140721.92227269_290X440X4.jpg"
        ],
        "约翰·马尔科维奇": [
            " 　　马尔科维奇生长在煤矿业发达的美国小镇本顿。他的家族在当地很有名，不仅旗下经营着一份报纸，而且他的父亲还是一本环境杂志的主编。有人将这个家族称作是“小镇上绝无仅有的一个”，约翰·马尔科维奇注定是要在这个家族里诞生的。70年代的时候，马尔科维奇考入了伊利诺伊大学戏剧系。1976年，马尔科维奇毕业后就加入了Steppenwolf剧团，从此就被戏剧的魔力深深地吸引了。时好时坏的剧团生活大约持续了6年，1982年的一天，马尔科维奇与剧团带着新作《真实的西部》来到纽约，这一次演出彻底改变了他的命运。",
            "http://img31.mtime.cn/ph/2014/10/15/154628.17339721_290X440X4.jpg"
        ],
        "文·瑞姆斯": [
            "",
            "http://img31.mtime.cn/ph/2014/04/30/111024.18600765_290X440X4.jpg"
        ],
        "尼克·齐兰德": [
            "",
            "http://img31.mtime.cn/ph/2014/03/19/161054.59544295_290X440X4.jpg"
        ],
        "史蒂夫·布西密": [
            " 　　作为演员，史蒂夫·布西密曾在大小银幕中塑造过无数让人记忆犹新的鲜活人物，虽然多以配角出场，但其出色的演技丝毫不差于主角的光彩。从初涉影坛至今，布西密已经出演了将近100部电影和电视剧，时值今日，这棵常青树依然屹立不倒。2002年，他以《幽灵世界》赢得独立精神奖和纽约影评人协会的最佳男配角奖，以及金球奖提名，而他为HBO执导的电视剧《黑道家族》的部分剧集也被艾美奖和美国导演工会提名。　　　　布西密出生在纽约的布鲁克林，在中学毕业前对表演产生了浓厚的兴趣，随后到曼哈顿学习表演，并开始创作和表演舞台剧。",
            "http://img31.mtime.cn/ph/2016/08/26/145403.46019927_290X440X4.jpg"
        ],
        "科尔姆·米尼": [
            " 科尔姆·米尼1953年出生于岛国爱尔兰的首府都柏林，14岁初始迷上表演这门艺术，初中毕业后进入了爱尔兰极具盛名的艾比（Abbey）戏剧学院。之后科尔姆·米尼被吸收为爱尔兰国家剧院演员在全英各大剧院的舞台上度过了8年表演生涯。",
            "http://img31.mtime.cn/ph/2012/10/10/144642.75960328_290X440X4.jpg"
        ],
        "雷切尔·蒂科汀": [
            "",
            "http://img5.mtime.cn/ph/2017/06/01/151013.49256127_290X440X4.jpg"
        ],
        "大卫·查普尔": [
            "",
            "http://img31.mtime.cn/ph/2013/07/09/172845.18495355_290X440X4.jpg"
        ],
        "麦凯尔泰·威廉逊": [
            "",
            "http://img31.mtime.cn/ph/2016/09/02/180618.32300064_290X440X4.jpg"
        ]
    }
}