{
    "title": "泰迪熊",
    "info": "   　　男孩约翰8岁在圣诞夜收到泰迪熊布偶当礼物，许愿“希望泰迪能与我说话”后，泰迪熊有了生命，成为他真正的朋友。某种神秘的力量，让他的愿望成真了。然而，当约翰跟他的泰迪熊一起度过欢乐童年，如今成为一个独立的大男人时，跟他形影不离的泰迪熊似乎变成他最大的包袱了。 　　这情况尤其在约翰遇到喜欢的对象时变得更加棘手，泰迪熊总是坏了他的好事，也惹毛了约翰的女友。于是约翰开始设法摆脱泰迪熊的纠缠，说服泰迪熊也能自己寻找好对象。看来似乎是要他的泰迪熊也能独立、成长，不要再依赖着他，但到头来，真正需要学会独立的，其实是约翰自己才对。",
    "comment": [
        "我就欣赏泰迪熊爱说真话的性格~\"一切都是你决定的啊,我是邀请你了,但是来不来是你自己选择的啊!\"juile看过 ",
        "段子污不停，友情爱情双丰收，人生赢家啊，贱熊有你的IMAX-让梦想更真实看过 ",
        "故事平平，部分情节少儿不宜。开朗的斯特法诺看过 ",
        "以为会有很多段子很多幽默，结果失望有点大～①-18o·虫虐·看过 ",
        "够污，小孩子不能随便看，会毁了玩具熊的形象的vivo照亮你的美看过 ",
        "太污了随风819看过 ",
        "与帕丁顿熊相比，泰迪熊口无遮掩，爱说黄段子，显得贱贱的，但这就是它自身的特色。电影娱乐性还不错，还算合格吧。Purphy看过 ",
        "够骚JimLiu看过 "
    ],
    "pic": [
        "http://img21.mtime.cn/mt/2012/04/05/121721.78765767_270X405X4.jpg"
    ],
    "actors": {
        "马克·沃尔伯格": [
            " 　　马克·沃尔伯格的母亲名叫阿尔玛，父亲名叫唐纳德，他有5个哥哥和3个姐姐。出生于美国波士顿，高中时候退学，后获GED资格(一般教育考试)。做过各种各样的工作包括瓦工，甚至因几次违法而被判罪。后独立组建Marky Mark and Funky Bunch乐队发行两张摇滚唱片并巡回演出(《人民的音乐》和《你要相信》)。《完美摇摆》赢得最佳舞曲，这首歌直至今天仍然很流行。他在舞台上的魅力在他脱去衬衫和裤子的时候就更加无法抵挡。1992年，他成为著名时装设计师凯文·克莱恩的内衣模特。他和超级名模凯特·摩丝在一起拍摄的几乎全裸的广告照片则令他备受争议。",
            "http://img31.mtime.cn/ph/2014/06/10/093108.15071862_290X440X4.jpg"
        ],
        "塞思·麦克法兰": [
            " 　　塞思·麦克法兰，美国编剧、制片人、导演和演员，甚至还是配音演员。他最有名的作品就是原创的美国动画系列《恶搞之家FamilyGuy》和美剧《美国老爸》。另外，他还是一系列短剧的编剧和制作人，曾两次获得艾美奖。他曾与二十世纪福克斯签署了一份新合同，而这份合同让他成为了有史以来薪酬最高的电视编剧，五年总共高达一亿美元，而热门美剧《迷失Lost》的创造者J.J.Abrams和Paramount以及WarnerBros签的5年合同总价格也才6千万美元。另外，他还是一系列短剧的编剧和制作人，曾两次获得艾美奖。2012年，成为第85届奥斯卡主持人。",
            "http://img31.mtime.cn/ph/2014/05/27/142311.47944513_290X440X4.jpg"
        ],
        "米拉·库妮丝": [
            " 米拉·库妮丝1983年生于前苏联的基辅(现乌克兰)，7岁时搬到了美国洛山矶，父母的职业分别是机械工程师和物理老师，还有一位从事生物化学研究的哥哥Mike。9岁时米拉·库妮丝一边上学，一边在课外去上“Beverly Hills Studio”的表演培训课程，此后通过这里的一次演出被娱乐经纪人Susan Curtis发掘。米拉·库妮丝参加《70年代秀》试镜当时让对方以为她很快过了生日就年满18岁，但其实只有14岁，结果成功地进入了剧组，在里面她的角色是比她大五岁艾什顿·库彻的女友。此后米娜的演艺道路十分顺利，赢得了很多影迷的喜爱。",
            "http://img31.mtime.cn/ph/2014/03/14/153412.40694927_290X440X4.jpg"
        ],
        "吉奥瓦尼·瑞比西": [
            " 　　意大利血统的美国演员吉奥瓦尼·瑞比西外表颇为孩子气，但在片中扮演的角色常常有着超乎常人的个性举动和歪打正着的人格魅力，和他一起站在镜头前的演员不管多么大牌随时都有被抢戏的危险。瑞比西出生在美国洛杉矶市，有一个小十五分钟的双胞胎妹妹，由于父母都在演艺圈工作，他不到十岁起便在各电视台剧集中“走街串巷”，首次引起注意凭借的是1995年出演《X档案》的精彩表现，之后他得到了《老友记》中菲比老弟的角色，这也是他迄今为止最为人所知的角色。",
            "http://img31.mtime.cn/ph/2016/09/06/160729.25114151_290X440X4.jpg"
        ],
        "劳拉·范德沃特": [
            "",
            "http://img31.mtime.cn/ph/2014/02/22/211256.78522253_290X440X4.jpg"
        ],
        "帕特里克·沃伯顿": [
            "",
            "http://img5.mtime.cn/ph/2017/01/10/143853.74497473_290X440X4.jpg"
        ],
        "乔尔·麦克哈尔": [
            "",
            "http://img31.mtime.cn/ph/2015/05/25/153912.54793945_290X440X4.jpg"
        ],
        "杰西卡·斯特普": [
            "",
            "http://img31.mtime.cn/ph/2014/02/22/213421.44986495_290X440X4.jpg"
        ],
        "梅丽莎·奥德维": [
            "",
            "http://img31.mtime.cn/ph/2014/02/22/220340.55460397_290X440X4.jpg"
        ],
        "杰西卡·巴斯": [
            "",
            "http://img31.mtime.cn/ph/2012/06/27/164155.12136541_290X440X4.jpg"
        ]
    }
}