{
    "title": "四大名捕2",
    "info": "   　　城郊命案发生，四大名捕前往现场缉凶，不料引出十五年前杀害无情全家之惨案，名捕们顺藤摸瓜，牵出各种隐情，上演了一连串精彩冒险。个人恩怨与天下苍生之间，名捕们该如何抉择？又怎料血战之后，更大的风暴紧接而来。",
    "comment": [
        "皇宫 棋局 阳光 影子 放弃 才可永不限量绝世好贱看过 ",
        "嗯，期待值比第一部后下降了一点，不过也还过得去咯，还是会期待后续……conan看过 ",
        "联名上书举报蔡相 然后被人反撸了。这帮兄弟要把盛家也干了，诸葛说领皇帝命来救人“皇恩浩荡”这事情搞半天皇帝知道？那还启奏个毛 直接把蔡相撸了啊 安老爷这么屌 直接上来把捕神撸了啊 这部编剧简直吃了屎 都是些什么玩意溅溅看过 ",
        "入了坑了不看完不舒服系列，第二部开始转为聊斋风格了吗，还有每一部都有两段姬瑶花洗澡戏，固定福利？从这部开始渐渐的能get到刘亦菲的演技了。奥瑟雅月汐看过 ",
        "这系列电影逐渐失控，越来越不着边际了，其他内容一如既往的平庸，当然特效还是出色的。于小谦谦看过 ",
        "陈嘉上是不是对“半身瘫痪”这个词的意思有什么误解？四大名捕这么明确的人设，这么适合照着拍的一堆故事(坑掉的不算，写完的也总是有不少的吧？)能瞎成这样我也是服。人物几乎全取自于会京师，除了成树的吴秀波似乎是仿的破烂王唐化(第一部的冰火功则像楚相玉)。可惜四大人设全崩。junf看过 ",
        "竟然把武侠拍成了魔幻，这让四大名捕在我心里分数直降wkxclvt看过 ",
        "M当然一起看啦。天王水瓶女看过 "
    ],
    "pic": [
        "http://img31.mtime.cn/mt/2013/11/11/142404.82285704_270X405X4.jpg"
    ],
    "actors": {
        "邓超": [
            "    邓超，内地著名男演员。生于江西南昌，从江西省文艺学校95级表演班毕业后，进入中央戏剧学院98级表演本科班学习，大学时主演话剧曾轰动一时。2002年开始出演电视剧，知名作品有《少年康熙》、《少年包青天3》等。与孙俪合作的《幸福像花儿一样》获观众热捧，好评不断。之后两人又合作《甜蜜蜜》，同样是备受关注。　　在荧屏上的走红也为邓超带来登上大银幕的机会，2007年他在冯小刚的影片《集结号》中亮相，小试牛刀，之后又出演《李米的猜想》和《爱呼2：爱情左右》两部影片。2010年，在《狄仁杰之通天帝国》的夺目表现让邓超获得第30届香港电影金像奖最佳男配角提名，但最终败给了《打擂台》的泰迪罗宾。",
            "http://img5.mtime.cn/ph/2019/07/18/103044.91037774_290X440X4.jpg"
        ],
        "刘亦菲": [
            " 　　刘亦菲生于武汉，父亲是大学教授，母亲是舞蹈演员。1995年，年仅8岁的刘亦菲，在中南商都第二届“童花杯”童装模特大奖赛中获得冠军。刘亦菲10岁时遭遇家庭变故，母亲为了让她受到更好的教育，便让她从小学退学，赴美国读书。　　　　　　　　　　　　　　　　　　　　　　　　　　2002年回到北京，制片人游建鸣在喝茶时看见了其任形象代言的房地产广告，当即决定由其出演《金粉世家》女二号白秀珠。之后，刘亦菲又被导演张纪中看中，在其导演的电视剧《天龙八部》、《神雕侠侣》中出演了王语嫣、小龙女。 2007年，才刚满20岁的刘亦菲出演了自己的第一部好莱坞大片《功夫之王》，与成龙、李连杰同台，从而推开了好莱坞大门。",
            "http://img5.mtime.cn/ph/2017/11/30/095944.74616582_290X440X4.jpg"
        ],
        "邹兆龙": [
            " 　　邹兆龙，又名倪星，1967年出生于台湾，5岁开始习武，12岁就以替身演员的身份开始了他的电影生涯。18岁邹兆龙主演了洪金宝导演的电影《全力反弹》，其后拜洪金宝为师，来到香港发展，成为洪家班的一员。他在香港拍摄了30多部电影，分别和洪金宝、元奎、徐克、袁和平等知名导演合作。邹兆龙曾四次与李连杰配戏，1994年的《中南海保镖》，他作为李连杰的死对头，和李连杰有几场精彩的打戏，同年拍摄的《倚天屠龙记之魔教教主》里他又是扮演迫害张无忌的宋青书，1995年他和李连杰合作拍摄了《赤子威龙》，1996年他第四和李连杰合作，在《冒险王》中再次对抗李连杰扮演的角色。",
            "http://img31.mtime.cn/ph/2014/03/14/154703.79067678_290X440X4.jpg"
        ],
        "郑中基": [
            " 　　香港艺人。父亲为香港音乐人，唱片公司高层。以歌手身份出道的郑中基，在出道之初被视为娱乐圈的二世祖。近年来多元发展，除了偶尔仍旧唱歌之外，主演的多部喜剧都很卖座，成为香港新一代的喜剧明星。如今又尝试做导演，2007年推出导演作品《心想事成》。2007年参演的《老港正传》中扮演黄秋生的儿子，获第27届香港电影金像奖最佳男配角。",
            "http://img5.mtime.cn/ph/2017/07/19/120827.56209004_290X440X4.jpg"
        ],
        "黄秋生": [
            " 　　香港演员。父亲是英国人，但幼年时就把妻儿抛在香港，黄称自己从未见过父亲。年少时为生活所迫，做过办公室助理，当过汽车修理厂学徒、装修工人。1984年加入亚视训练班。　　1985年出演电影《花街时代》后自觉演技未够水准，入香港演艺学院深造，成为该校第一届毕业生。后入无线电视台，参演过《他来自江湖》、《天若有情》、《人海骄阳》等剧集。1990年起全面投入电影事业，参演《舞牛》(1990，方育平执导)、《表姐，妳好嘢！》(1991)、《侠盗高飞》、《我爱扭纹柴》(1992)等。",
            "http://img31.mtime.cn/ph/2016/01/08/100926.49073136_290X440X4.jpg"
        ],
        "江一燕": [
            " 　　原名江燕，1999年9月与戴琦、戴梦瑶、李薇薇和杨若榴成立“漂亮宝贝”演唱组，2000年7月在电视连续剧《同学，你好！》中友情出演，2000年10月参加电视连续剧《真榜》的拍摄。之后出演的作品有《葛定国同志的夕阳红》(饰段小玲)、《与你同在的夏天》(饰李明馨)、《母亲》(饰小女儿文小秀)、《星火》(饰梅春/梅春娘)、《错爱》(饰谢晓英)、《我们无处安放的青春》(饰周蒙)。 　　2000年为电视剧《插翅难逃》演唱片尾曲，2006年发行EP《用爱呼吸》，2008年与吴镇宇、余男合作《双食记》，演出颇受好评。同时也出演了陆川导演的新片《南京！南京！》。",
            "http://img31.mtime.cn/ph/2016/09/02/172907.12588548_290X440X4.jpg"
        ],
        "吴秀波": [
            " 　　吴秀波，内地男演员。1968年出生于北京，1988年毕业于中央戏剧学院表演系。1995年辞去中国铁路文工团话剧团的工作，签约唱片公司成为歌手，并发行过一张专辑《爱之战》。之后曾从事过电视剧监制、音乐编辑、商人等职业，于2002年回归表演。出演过《黎明之前》、《道可道》、《相思树》、《兄弟门》、《嫁衣》、《剑谍》、《大爱无敌》等多部热播剧，以《黎明之前》中“刘新杰”一角成名。2012年成功主演高热播剧《心术》，受到广泛好评。2012年，与汤唯搭档主演浪漫爱情喜剧《北京遇上西雅图》，讲述了一段“败金女”与“落魄大叔”的异国爱情故事。",
            "http://img31.mtime.cn/ph/2014/08/08/114611.61511108_290X440X4.jpg"
        ],
        "柳岩": [
            " 　　内地新生代当红女主播之一，出道以来特别是近年来似乎一直在走性感路线，常因性感、暴露的穿着而引来话题。2011年，在《画壁》中扮演最性感仙女“云梅”，大放异彩。2012年出演了《哭笑不得》、《十二星座离奇事件》、《嫁个100分男人》等电影。",
            "http://img5.mtime.cn/ph/2017/07/27/094457.87514630_290X440X4.jpg"
        ],
        "成泰燊": [
            " 　　又名成太生。出生于山西交城的一个工人家庭。1993年进入中央戏剧学院表演导演混合本科班。毕业后，被分配到西安电影制片厂导演室，他在著名导演黄建新的影片《睡不着》中担任导演助理、场记与配角演员。　　成泰燊考中戏前演过几年话剧，更早的时候，当过炼钢工人，所以在《世界》里演一个进城后当上保安的农民，他很有生活。之前一直默默无闻的成泰燊，在2001年主演导演朱文的电影《海鲜》就荣获58届威尼斯电影节评审团特别奖，他本人也因该片摘得法国南特三大州国际电影节的影帝桂冠。",
            "http://img5.mtime.cn/ph/2019/10/16/153228.27627564_290X440X4.jpg"
        ],
        "邓萃雯": [
            " 邓萃雯1985年毕业于无线电视艺员进修班节2期。曾有“翁美玲的接班人”“最佳古装美人”等封号。凭借最近无线的宫廷剧《金枝欲孽》再攀演艺高峰。",
            "http://img31.mtime.cn/ph/2014/03/14/154738.29687502_290X440X4.jpg"
        ]
    }
}