{
    "title": "速度与激情3",
    "info": "   　　为了避免再度惹事生非，街头赛车手尚恩被送回东京与专制的军人父亲同住，在那他发现了“飘移”的技术。为东京山道赛车深深着迷的他，无意中杠上了有“飘移之王”名号的地下车手DK，然而奇逢对手初尝败绩，尚恩欠下了一屁股的债，被迫进入东京底层社会想尽办法还债。然而热血的尚恩不会止步于失败面前，东京狂飙正式开场...... ",
    "comment": [
        "还不错的，好像都说这一部差周末夜狂热看过 ",
        "我得漂～得漂～得意的漂～小姜1169106看过 ",
        "没有太烂，格局变小，专注漂移其实还行，只是剧本简直校园剧。蝙蝠俠看过 ",
        "只有赛车的部分还可以，其他的地方毫无亮点。彭小母看过 ",
        "很好看，飙车姿势开启绝版男人dk看过 ",
        "重温一遍1到8，再反观来看3确实很另类。影评风向都觉得林导大逆不道的抛弃了速度与激情，但你们忽略了赛车真正的魅力，不是比肌肉拼蛮力，故事在东京，这是亚洲领域赛车的灵魂弯道。炫酷的漂移智慧才是将赛车的性能发挥到极致，感受车轮的每次震动，人机合一的摩擦骚操作。这是玩车的高手追求的至高境界。多米克想要在车的领域称王，来到亚洲干不过飘逸，说不过去吧。素鸡系列后续加入更多炫目的车技，但剧情脑残度暴增，真是观众花智商税买的春。m2box看过 ",
        "这个彩蛋埋的很早啊，也很好vivo照亮你的美看过 ",
        "比预期的好一丢丢伦夕看过 "
    ],
    "pic": [
        "http://img5.mtime.cn/mg/2016/12/30/113237.71755644_270X405X4.jpg"
    ],
    "actors": {
        "卢卡斯·布莱克": [
            "",
            "http://img31.mtime.cn/ph/2014/02/22/195336.81334948_290X440X4.jpg"
        ],
        "布莱恩·泰": [
            "",
            "http://img31.mtime.cn/ph/2014/03/14/152707.55734166_290X440X4.jpg"
        ],
        "纳塔莉·凯利": [
            "",
            "http://img5.mtime.cn/ph/2017/08/30/150329.59327140_290X440X4.jpg"
        ],
        "杰森·托宾": [
            "",
            "http://img31.mtime.cn/ph/2014/02/22/212433.26793067_290X440X4.jpg"
        ],
        "千叶真一": [
            " 　　出生在日本福冈市。父亲是一名军事测试飞行员。他年轻的时候热衷体操，以他的天赋足以参加奥运会的比赛，但是后来由于伤病，使他不得不退出。在大学期间他对空手道产生了浓厚的兴趣，并在传奇人物Mas Oyama的指导下，很快拿到了第一条黑带。1960年，他被东映公司发现，于是就这样开始了自己的银幕之路。他的第一部电影是1961年的《Invasion of the Neptune Men》。接下来的10年，千叶真一都在扮演着言语少，武功强的壮男这类角色。由于他精通藉空手道，柔道等武艺。在1974 年出演了武打巨星李小龙的《The Streetfighter》。后来千叶真一又继续拍摄了同一题材的电影，产生了很大的反响。",
            "http://img21.mtime.cn/ph/2011/06/08/151844.45448983_290X440X4.jpg"
        ],
        "丹尼尔·博克": [
            "",
            "http://img31.mtime.cn/ph/2014/02/22/211851.50711323_290X440X4.jpg"
        ]
    }
}